MerWebPy/__init__.py
MerWebPy-1.0.0.dist-info/LICENSE
MerWebPy-1.0.0.dist-info/METADATA
MerWebPy-1.0.0.dist-info/WHEEL
MerWebPy-1.0.0.dist-info/top_level.txt
MerWebPy-1.0.0.dist-info/RECORD
