Metadata-Version: 2.1
Name: MerWebPy
Version: 1.0.0
Summary: UNKNOWN
Home-page: https://github.com/kessec/MerWebPy
Author-email: muki@kessec.com
License: MIT
Keywords: merriam webster dictionary query database word noun verb adjective
Platform: UNKNOWN
Classifier: License :: OSI Approved :: MIT License
Classifier: Programming Language :: Python :: 3
Classifier: Programming Language :: Python :: 3.8
Classifier: Operating System :: OS Independent
Requires-Dist: requests
